chart/__init__.py
chart/example.py
hallred_chart-0.0.3.dist-info/LICENSE
hallred_chart-0.0.3.dist-info/METADATA
hallred_chart-0.0.3.dist-info/WHEEL
hallred_chart-0.0.3.dist-info/top_level.txt
hallred_chart-0.0.3.dist-info/RECORD
