Metadata-Version: 2.1
Name: hallred-chart
Version: 0.0.3
Summary: Data analytics and charting made easier
Home-page: https://github.com/hasta13/chart
Author: Hal Allred
Author-email: hallred@gmail.com
License: UNKNOWN
Project-URL: Bug Tracker, https://github.com/hasta13/chart/issues
Platform: UNKNOWN
Classifier: Programming Language :: Python :: 3
Classifier: License :: OSI Approved :: MIT License
Classifier: Operating System :: OS Independent
Requires-Python: >=3.6
License-File: LICENSE
